pucoti/__init__.py
pucoti/__main__.py
pucoti/activity_tracker.py
pucoti/app.py
pucoti/assets.py
pucoti/base_config.py
pucoti/callback.py
pucoti/config.py
pucoti/constants.py
pucoti/context.py
pucoti/controller.py
pucoti/db.py
pucoti/dfont.py
pucoti/platforms.py
pucoti/purpose.py
pucoti/pygame_utils.py
pucoti/server.py
pucoti/server_comunication.py
pucoti/telemetry.py
pucoti/time_utils.py
pucoti/assets/Bevan-Regular.ttf
pucoti/assets/OFL-Bevan.txt
pucoti/assets/bell.mp3
pucoti/assets/icons/help-circle.png
pucoti/assets/icons/home.png
pucoti/assets/icons/list.png
pucoti/assets/icons/maximize-2.png
pucoti/assets/icons/pucoti_icon.ico
pucoti/assets/icons/pucoti_icon.png
pucoti/assets/icons/settings.png
pucoti/assets/icons/users.png
pucoti/screens/base_screen.py
pucoti/screens/help_screen.py
pucoti/screens/main_screen.py
pucoti/screens/purpose_history_screen.py
pucoti/screens/social_screen.py
pucoti/screens/start_screen.py
pucoti/widgets/sentence_edit.py
pucoti/widgets/text_edit.py
pucoti-0.12.6.dist-info/METADATA
pucoti-0.12.6.dist-info/WHEEL
pucoti-0.12.6.dist-info/entry_points.txt
pucoti-0.12.6.dist-info/licenses/COPYING
pucoti-0.12.6.dist-info/RECORD
