Metadata-Version: 2.4
Name: pucoti
Version: 0.12.6
Summary: A Purposeful Countdown Timer
Project-URL: Homepage, https://github.com/ddorn/pucoti
Project-URL: Repository, https://github.com/ddorn/pucoti
License: GPL-3.0
License-File: COPYING
Keywords: countdown,gui,pygame,timer
Requires-Python: >=3.12
Requires-Dist: desktop-notifier>=6.1.1
Requires-Dist: luckypot>=0.1.1
Requires-Dist: platformdirs>=4.3.6
Requires-Dist: pydantic>=2.9.2
Requires-Dist: pygame-ce>=2.5.2
Requires-Dist: pyobjc-framework-cocoa==10.3.1; sys_platform == 'darwin'
Requires-Dist: pyyaml>=6.0.2
Requires-Dist: pyzmq>=26.2.0
Requires-Dist: requests>=2.32.3
Requires-Dist: ruamel-yaml>=0.18.6
Requires-Dist: typer>=0.13.0
Requires-Dist: umami-analytics>=0.2.20
